README.rst
setup.py
hashed/__init__.py
hashed/data/index
hashed/data/index-1
hashed/data/index.old
hashed/data/wordlist
hashedwords.egg-info/PKG-INFO
hashedwords.egg-info/SOURCES.txt
hashedwords.egg-info/dependency_links.txt
hashedwords.egg-info/top_level.txt