Metadata-Version: 1.1
Name: hashedwords
Version: 2.0.0
Summary: A module that converts hexadecimal digits into strings of words, and back
Home-page: https://github.com/RemyPorter/hashed
Author: Remy Porter
Author-email: remyporter@jetpackshark.com
License: MIT
Keywords: development hashes words
Platform: UNKNOWN
Classifier: Development Status :: 3 - Alpha
Classifier: Intended Audience :: Developers
Classifier: Topic :: Software Development :: Build Tools
Classifier: License :: OSI Approved :: MIT License
Classifier: Programming Language :: Python :: 3
Classifier: Programming Language :: Python :: 3.2
Classifier: Programming Language :: Python :: 3.3
Classifier: Programming Language :: Python :: 3.4
